UmbrellaReminder.py
UmbrellaReminder-0.0.2.dist-info/LICENSE
UmbrellaReminder-0.0.2.dist-info/METADATA
UmbrellaReminder-0.0.2.dist-info/WHEEL
UmbrellaReminder-0.0.2.dist-info/top_level.txt
UmbrellaReminder-0.0.2.dist-info/RECORD
