Metadata-Version: 2.1
Name: UmbrellaReminder
Version: 0.0.2
Summary: A Python package which scrapes weather data from google and sends umbrella reminders to specified email at specified time daily. 
Home-page: https://github.com/VinayEdula/UmbrellaReminder
Author: Edula Vinay Kumar Reddy
License: UNKNOWN
Keywords: weather,Reminder,scraping,Rain Reminder,Umbrella Reminder,Weather Reminder
Platform: UNKNOWN
Classifier: Programming Language :: Python :: 3
Classifier: License :: OSI Approved :: MIT License
Classifier: Operating System :: OS Independent
Requires-Python: >=3.6
Requires-Dist: requests
Requires-Dist: schedule
Requires-Dist: beautifulsoup4
